way2enjoypy/__init__.py
way2enjoypy/client.py
way2enjoypy/errors.py
way2enjoypy/result.py
way2enjoypy/result_meta.py
way2enjoypy/source.py
way2enjoypy/version.py
way2enjoypy/data/cacert.pem
way2enjoypy-1.0.1.dist-info/METADATA
way2enjoypy-1.0.1.dist-info/WHEEL
way2enjoypy-1.0.1.dist-info/top_level.txt
way2enjoypy-1.0.1.dist-info/RECORD
