Metadata-Version: 2.1
Name: way2enjoypy
Version: 1.0.1
Summary: way2enjoy API client.
Home-page: https://way2enjoy.com/developers
Author: way2enjoy
Author-email: support@way2enjoy.com
License: MIT
Platform: UNKNOWN
Classifier: Development Status :: 5 - Production/Stable
Classifier: Intended Audience :: Developers
Classifier: Natural Language :: English
Classifier: License :: OSI Approved :: MIT License
Classifier: Programming Language :: Python
Classifier: Programming Language :: Python :: 2.6
Classifier: Programming Language :: Python :: 2.7
Classifier: Programming Language :: Python :: 3
Classifier: Programming Language :: Python :: 3.3
Classifier: Programming Language :: Python :: 3.4
Requires-Dist: requests (<3.0.0,>=2.7.0)
Provides-Extra: test
Requires-Dist: nose (<2.0,>=1.3) ; extra == 'test'
Requires-Dist: httpretty (<1.0.0,>=0.8.10) ; extra == 'test'
